btQuant/__init__.py
btQuant/bootstrap.py
btQuant/dimensionReduction.py
btQuant/distributions.py
btQuant/econometrics.py
btQuant/factor.py
btQuant/fit.py
btQuant/ml.py
btQuant/options.py
btQuant/plot.py
btQuant/portfolio.py
btQuant/risk.py
btQuant/sim.py
btquant-0.1.9.dist-info/licenses/LICENSE
btquant-0.1.9.dist-info/METADATA
btquant-0.1.9.dist-info/WHEEL
btquant-0.1.9.dist-info/top_level.txt
btquant-0.1.9.dist-info/RECORD
