Metadata-Version: 2.4
Name: btQuant
Version: 0.1.9
Summary: Boyko Terminal Quantitative Finance Python Package Companion.
Author-email: Brayden Boyko <braydenboyko@boykowealth.com>
License: GPL
Project-URL: Homepage, https://github.com/boykowealth/btQuant
Requires-Python: >=3.10
License-File: LICENSE
Requires-Dist: numpy>=1.23
Requires-Dist: scipy>=1.10
Requires-Dist: plotly>=5.0
Requires-Dist: pandas>=1.5
Dynamic: license-file
